opentriviadb/__init__.py
opentriviadb/client.py
opentriviadb/errors.py
opentriviadb/questions.py
opentriviadb-0.1.0.dist-info/LICENSE
opentriviadb-0.1.0.dist-info/METADATA
opentriviadb-0.1.0.dist-info/WHEEL
opentriviadb-0.1.0.dist-info/top_level.txt
opentriviadb-0.1.0.dist-info/RECORD
