Metadata-Version: 2.1
Name: opentriviadb
Version: 0.1.0
Summary: An asynchronous wrapper for the Open Trivia DB API.
Home-page: https://github.com/parafoxia/opentriviadb
Author: Ethan Henderson
Author-email: ethan.henderson.1998@gmail.com
License: BSD 3-Clause 'New' or 'Revised' License
Project-URL: Documentation, https://parafoxia.github.io/opentriviadb
Project-URL: Source, https://github.com/parafoxia/opentriviadb
Project-URL: Bug Tracker, https://github.com/parafoxia/opentriviadb/issues
Project-URL: CI, https://github.com/parafoxia/opentriviadb/actions
Project-URL: Changelog, https://github.com/parafoxia/opentriviadb/releases
Classifier: Development Status :: 3 - Alpha
Classifier: Framework :: AsyncIO
Classifier: Intended Audience :: Developers
Classifier: License :: OSI Approved :: BSD License
Classifier: Natural Language :: English
Classifier: Operating System :: MacOS
Classifier: Operating System :: Microsoft :: Windows
Classifier: Operating System :: OS Independent
Classifier: Operating System :: POSIX
Classifier: Operating System :: Unix
Classifier: Programming Language :: Python :: 3
Classifier: Programming Language :: Python :: 3 :: Only
Classifier: Programming Language :: Python :: 3.7
Classifier: Programming Language :: Python :: 3.8
Classifier: Programming Language :: Python :: 3.9
Classifier: Programming Language :: Python :: 3.10
Classifier: Programming Language :: Python :: 3.11
Classifier: Programming Language :: Python :: Implementation :: CPython
Classifier: Programming Language :: Python :: Implementation :: PyPy
Classifier: Topic :: Internet
Classifier: Topic :: Internet :: WWW/HTTP
Classifier: Typing :: Typed
Requires-Python: >=3.7.0,<3.13
License-File: LICENSE
Requires-Dist: aiohttp (<4,>=3.7.1)
